agro/__init__.py
agro/cli.py
agro/committer.py
agro/config.py
agro/core.py
agro-0.1.8.dist-info/licenses/LICENSE.txt
agro-0.1.8.dist-info/METADATA
agro-0.1.8.dist-info/WHEEL
agro-0.1.8.dist-info/entry_points.txt
agro-0.1.8.dist-info/top_level.txt
agro-0.1.8.dist-info/RECORD
