Metadata-Version: 2.4
Name: agro
Version: 0.1.8
Summary: CLI wrapper for CLI-agents
Author-email: Will Sutton <wsutton17@gmail.com>
License: MIT
Project-URL: Homepage, https://github.com/sutt/agro
Requires-Python: >=3.9
License-File: LICENSE.txt
Requires-Dist: PyYAML
Requires-Dist: argcomplete
Provides-Extra: dev
Requires-Dist: build>=1.2.2.post1; extra == "dev"
Requires-Dist: twine>=6.1.0; extra == "dev"
Provides-Extra: test
Requires-Dist: pytest>=8.4.1; extra == "test"
Dynamic: license-file
